scbamtools
