Metadata-Version: 2.1
Name: scbamtools
Version: 0.8.8
Summary: High performance Cython + Python tools to process BAM files with tags as they arise in single-cell sequencing
Home-page: https://github.com/marvin-jens/scbamtools
Author: Marvin Jens
Author-email: marvin.jens@charite.de
License: MIT License
Project-URL: Homepage, https://github.com/marvin-jens/scbamtools
Project-URL: Repository, https://github.com/marvin-jens/scbamtools.git
Project-URL: Issues, https://github.com/marvin-jens/scbamtools/issues
Keywords: bioinformatics,single cell,BAM,SAM,CRAM,genetics,cell barcode,biology,gene expression
Classifier: Development Status :: 3 - Alpha
Classifier: Intended Audience :: Science/Research
Classifier: Topic :: Scientific/Engineering :: Bio-Informatics
Classifier: License :: OSI Approved :: MIT License
Requires-Python: >=3.8
License-File: LICENSE
Requires-Dist: mrfifo
Requires-Dist: cython
Requires-Dist: cutadapt
Requires-Dist: numpy
Requires-Dist: ncls
